stringmix/__init__.py
stringmix-0.3.dist-info/LICENSE.txt
stringmix-0.3.dist-info/METADATA
stringmix-0.3.dist-info/WHEEL
stringmix-0.3.dist-info/top_level.txt
stringmix-0.3.dist-info/RECORD
