Metadata-Version: 2.1
Name: stringmix
Version: 0.3
Summary: Provide a string, and receive a shuffled version of that string.
Home-page: UNKNOWN
Author: Aaron Logigan
Author-email: aaron.logigan@outlook.com
License: UNKNOWN
Platform: UNKNOWN
Classifier: Programming Language :: Python :: 3
Classifier: License :: OSI Approved :: MIT License
Classifier: Operating System :: OS Independent
License-File: LICENSE.txt
